imagemodal/__init__.py
imagemodal/models.py
imagemodal/settings.py
imagemodal/views.py
imagemodal/xblocks.py
imagemodal/mixins/__init__.py
imagemodal/mixins/fragment.py
imagemodal/mixins/scenario.py
imagemodal/public/draggabilly.pkgd.min.js
imagemodal/public/view.css
imagemodal/public/view.js
imagemodal/public/view.less
imagemodal/scenarios/image-modal-many.xml
imagemodal/scenarios/image-modal-single.xml
imagemodal/templates/view.html
imagemodal/translations/en/LC_MESSAGES/django.po
imagemodal/translations/en/LC_MESSAGES/text.po
openedx_xblock_image_modal-4.1.0.dist-info/LICENSE
openedx_xblock_image_modal-4.1.0.dist-info/METADATA
openedx_xblock_image_modal-4.1.0.dist-info/WHEEL
openedx_xblock_image_modal-4.1.0.dist-info/entry_points.txt
openedx_xblock_image_modal-4.1.0.dist-info/top_level.txt
openedx_xblock_image_modal-4.1.0.dist-info/RECORD
